epub_get_author.py
epubgrep.py
epubgrep-0.11.0.dist-info/licenses/LICENSE
epubgrep-0.11.0.dist-info/METADATA
epubgrep-0.11.0.dist-info/WHEEL
epubgrep-0.11.0.dist-info/entry_points.txt
epubgrep-0.11.0.dist-info/top_level.txt
epubgrep-0.11.0.dist-info/RECORD
