Metadata-Version: 2.4
Name: epubgrep
Version: 0.11.0
Summary: Grep through EPub files
Author-email: Matěj Cepl <mcepl@cepl.eu>
License-Expression: MIT
Project-URL: homepage, https://git.sr.ht/~mcepl/epubgrep
Project-URL: repository, https://git.sr.ht/~mcepl/epubgrep
Classifier: Environment :: Console
Classifier: Intended Audience :: Information Technology
Classifier: Operating System :: OS Independent
Classifier: Programming Language :: Python :: 3
Classifier: Programming Language :: Python :: 3.6
Classifier: Programming Language :: Python :: 3.7
Classifier: Programming Language :: Python :: 3.8
Classifier: Programming Language :: Python :: 3.9
Classifier: Programming Language :: Python :: 3.10
Classifier: Programming Language :: Python :: 3.11
Classifier: Programming Language :: Python :: 3.12
Classifier: Topic :: Software Development :: Libraries :: Python Modules
License-File: LICENSE
Requires-Dist: epub_meta
Dynamic: license-file
